vault_service/__init__.py
vault_service/utils.py
vault_service/models/__init__.py
vault_service/models/model.py
vault_service/models/response.py
vault_service/services/__init__.py
vault_service/services/vault_controller.py
vault_service-1.3.2.dist-info/licenses/LICENSE.txt
vault_service-1.3.2.dist-info/METADATA
vault_service-1.3.2.dist-info/WHEEL
vault_service-1.3.2.dist-info/top_level.txt
vault_service-1.3.2.dist-info/RECORD
