Metadata-Version: 2.4
Name: vault-service
Version: 1.3.2
Summary: A reusable python vault utility service for other projects to use hashicorp vault
Author: Ankush Bansal
Author-email: ankush.bansal@asato.ai
Requires-Python: >=3.8
License-File: LICENSE.txt
Requires-Dist: hvac>=2.3.0
Requires-Dist: python-dotenv>=1.0.1
Requires-Dist: pydantic>=2.9.2
Dynamic: author
Dynamic: author-email
Dynamic: description
Dynamic: description-content-type
Dynamic: license-file
Dynamic: requires-dist
Dynamic: requires-python
Dynamic: summary
